jk_contract/__init__.py
jk_contract/jk_contract.py
jk_contract/regex_dictionary.py
jk_contract-1.1.5.dist-info/LICENSE
jk_contract-1.1.5.dist-info/METADATA
jk_contract-1.1.5.dist-info/WHEEL
jk_contract-1.1.5.dist-info/entry_points.txt
jk_contract-1.1.5.dist-info/top_level.txt
jk_contract-1.1.5.dist-info/RECORD
