Metadata-Version: 2.1
Name: jk-contract
Version: 1.1.5
Summary: Toolkit with functions designed to extract various information from JK contracts
Home-page: https://github.com/OvergrownBaby/jk_contract
Author: Andy Tsang Yuk Lun
Author-email: Andy <andytsangyuklun@gmail.com>
License: Copyright (c) 2018 The Python Packaging Authority        
Project-URL: Homepage, https://github.com/OvergrownBaby/jk_contract_toolkit
Project-URL: Bug Tracker, https://github.com/OvergrownBaby/jk_contract_toolkit/issues
Classifier: Programming Language :: Python :: 3
Classifier: License :: OSI Approved :: MIT License
Classifier: Operating System :: OS Independent
Requires-Python: >=3.7, <4
License-File: LICENSE
Requires-Dist: docx2python
Requires-Dist: regex
Requires-Dist: pandas
Requires-Dist: numpy
